Metadata-Version: 2.1
Name: rubicon-objc-pythonista
Version: 0.4.7
Summary: A bridge between an Objective C runtime environment and Python.
Author-email: Russell Keith-Magee <russell@keith-magee.com>
Maintainer-email: BeeWare Team <team@beeware.org>
License: New BSD
Project-URL: Homepage, https://beeware.org/rubicon
Project-URL: Funding, https://beeware.org/contributing/membership/
Project-URL: Documentation, https://rubicon-objc.readthedocs.io/en/latest/
Project-URL: Tracker, https://github.com/beeware/rubicon-objc/issues
Project-URL: Source, https://github.com/beeware/rubicon-objc
Keywords: iOS,Objective C
Classifier: Development Status :: 4 - Beta
Classifier: Intended Audience :: Developers
Classifier: License :: OSI Approved :: BSD License
Classifier: Programming Language :: Objective C
Classifier: Programming Language :: Python :: 3
Classifier: Programming Language :: Python :: 3.8
Classifier: Programming Language :: Python :: 3.9
Classifier: Programming Language :: Python :: 3.10
Classifier: Programming Language :: Python :: 3.11
Classifier: Programming Language :: Python :: 3.12
Classifier: Programming Language :: Python :: 3 :: Only
Classifier: Topic :: Software Development
Requires-Python: >=3.8
License-File: LICENSE
Provides-Extra: dev
Requires-Dist: pytest ==7.4.3 ; extra == 'dev'
Requires-Dist: pytest-tldr ==0.2.5 ; extra == 'dev'
Requires-Dist: setuptools-scm ==8.0.4 ; extra == 'dev'
Requires-Dist: tox ==4.11.4 ; extra == 'dev'
Requires-Dist: pre-commit ==3.5.0 ; (python_version < "3.9") and extra == 'dev'
Requires-Dist: pre-commit ==3.6.0 ; (python_version >= "3.9") and extra == 'dev'
Provides-Extra: docs
Requires-Dist: furo ==2023.9.10 ; extra == 'docs'
Requires-Dist: pyenchant ==3.2.2 ; extra == 'docs'
Requires-Dist: sphinx-tabs ==3.4.4 ; extra == 'docs'
Requires-Dist: sphinx-autobuild ==2021.3.14 ; extra == 'docs'
Requires-Dist: sphinx-copybutton ==0.5.2 ; extra == 'docs'
Requires-Dist: sphinxcontrib-spelling ==8.0.0 ; extra == 'docs'
Requires-Dist: sphinx ==7.1.2 ; (python_version < "3.9") and extra == 'docs'
Requires-Dist: sphinx ==7.2.6 ; (python_version >= "3.9") and extra == 'docs'
